Workbook

Sheet Dashboard
B2: ▍▍▍ PERFORMX | D2: ENTERPRISE PERFORMANCE DASHBOARD | L2: REPORTING PERIOD
B3: INSIGHT. ANALYZE. GROW | D3: Executive Overview | L3: MAY 1 – MAY 31, 2024
B5: 📊 Dashboard | D5: TOTAL REVENUE | G5: TOTAL COST | J5: GROSS PROFIT | M5: GROSS MARGIN
D6: =Raw_Data!E16 -> 0 | G6: =Raw_Data!F16 -> 0 | J6: =Raw_Data!G16 -> 0 | M6: =0.27*(Raw_Data!E16/Raw_Data!E16) -> 0
D7: ="▲ " & TEXT((Raw_Data!E16-Raw_Data!I16)/Raw_Data!I16, "0.0%") & " vs Apr 1 – Apr 30, 2024" -> 0 | G7: ="▼ " & TEXT(ABS((Raw_Data!F16-Raw_Data!J16)/Raw_Data!J16), "0.0%") & " vs Apr 1 – Apr 30, 2024" -> 0 | J7: ="▲ " & TEXT((Raw_Data!G16-Raw_Data!K16)/Raw_Data!K16, "0.0%") & " vs Apr 1 – Apr 30, 2024" -> 0 | M7: ="▲ " & TEXT((0.27-0.239)*100, "0.0") & " pp vs Apr 1 – Apr 30, 2024" -> 0
B8: 💲 Revenue
B11: 📈 Profitability
B14: 🌐 Regional Sales
B17: 📦 Products
B20: 📥 Export to PDF
D26: KEY METRICS
D27: METRIC | F27: ACTUAL | G27: BUDGET | H27: VARIANCE | I27: VAR. % | J27: PRIOR PERIOD | K27: PRIOR PERIOD % | L27: YTD TOTAL | N27: YTD %
D28: Total Revenue | F28: =Raw_Data!E16 -> 0 | G28: =Raw_Data!L16 -> 0 | H28: =F28-G28 -> 0 | I28: =H28/G28 -> 0 | J28: =Raw_Data!I16 -> 0 | K28: =(F28-J28)/J28 -> 0 | L28: =Raw_Data!O16 -> 0 | N28: =((F28-J28)/J28)*0.84 -> 0
D29: Total Cost | F29: =Raw_Data!F16 -> 0 | G29: =Raw_Data!M16 -> 0 | H29: =F29-G29 -> 0 | I29: =H29/G29 -> 0 | J29: =Raw_Data!J16 -> 0 | K29: =(F29-J29)/J29 -> 0 | L29: 3037000 | N29: -0.062
D30: Gross Profit | F30: =Raw_Data!G16 -> 0 | G30: =Raw_Data!N16 -> 0 | H30: =F30-G30 -> 0 | I30: =H30/G30 -> 0 | J30: =Raw_Data!K16 -> 0 | K30: =(F30-J30)/J30 -> 0 | L30: 40065000 | N30: 0.153
D31: Gross Margin | F31: =0.27*(F28/F28) -> 0 | G31: =0.23*(G28/G28) -> 0 | H31: =(F31-G31)*100 -> 0 | I31: – | J31: =0.239*(J28/J28) -> 0 | K31: =(F31-J31)*100 -> 0 | L31: 0.266 | N31: 2.4
D33: All values in USD. Percentages represent change vs prior period unless noted. | L33: Data as of May 31, 2024

Sheet Revenue
B2: ▍▍▍ PERFORMX | D2: REVENUE PERFORMANCE & ACQUISITION CHANNELS
B3: INSIGHT. ANALYZE. GROW | D3: Channel Economics, Conversion Efficiency & Monthly Attainment Analysis
B5: 📊 Dashboard | D5: INBOUND REVENUE | F5: TOP PERFORMING CHANNEL | H5: AVG DEAL SIZE | J5: ANNUAL RUN-RATE (ARR)
D6: =SUM(Raw_Data!I20:I26) -> 0 | F6: Referral ($1.95M) | H6: $42,500 | J6: =Raw_Data!E16*12 -> 0
D7: ▲ 14.8% vs Last Month | F7: ▲ 25.3% Growth YoY | H7: ▲ 8.4% Expansion | J7: ▲ Target on Track
B8: 💲 Revenue
D9: CHANNEL DETAILED BREAKDOWN & TARGET ATTAINMENT
D10: Acquisition Channel | E10: Budget Target ($) | F10: Actual Revenue ($) | G10: Variance ($) | H10: Attainment % | I10: YoY Growth % | J10: CAC ($) | K10: LTV:CAC
B11: 📈 Profitability | D11: Email Campaigns | E11: 700000 | F11: 750000 | G11: =F11-E11 -> 0 | H11: =F11/E11 -> 0 | I11: 0.165 | J11: 4200 | K11: 6.2
D12: Social Media Ads | E12: 650000 | F12: 700000 | G12: =F12-E12 -> 0 | H12: =F12/E12 -> 0 | I12: 0.165 | J12: 5800 | K12: 4.8
D13: Organic Web Search | E13: 1100000 | F13: 1200000 | G13: =F13-E13 -> 0 | H13: =F13/E13 -> 0 | I13: 0.165 | J13: 1800 | K13: 12.4
B14: 🌐 Regional Sales | D14: Strategic Partners | E14: 1500000 | F14: 1650000 | G14: =F14-E14 -> 0 | H14: =F14/E14 -> 0 | I14: 0.165 | J14: 8500 | K14: 5.5
D15: Direct Enterprise Sales | E15: 1400000 | F15: 1450000 | G15: =F15-E15 -> 0 | H15: =F15/E15 -> 0 | I15: 0.165 | J15: 12000 | K15: 4.2
D16: Client Referrals | E16: 1800000 | F16: 1950000 | G16: =F16-E16 -> 0 | H16: =F16/E16 -> 0 | I16: 0.165 | J16: 1500 | K16: 15.8
B17: 📦 Products | D17: Other Paid Channels | E17: 2000000 | F17: 2100000 | G17: =F17-E17 -> 0 | H17: =F17/E17 -> 0 | I17: 0.165 | J17: 4900 | K17: 5.1
B20: 📥 Export to PDF

Sheet Profitability
B2: ▍▍▍ PERFORMX | D2: PROFITABILITY & FINANCIAL STATEMENTS
B3: INSIGHT. ANALYZE. GROW | D3: Cost of Goods Sold (COGS), OpEx Breakdown & Net Operating Income
B5: 📊 Dashboard | D5: GROSS PROFIT | F5: TOTAL OPEX | H5: EBITDA | J5: NET PROFIT
D6: =Raw_Data!G16 -> 0 | F6: $3,180,000 | H6: $5,456,000 | J6: $4,364,800
D7: ▲ 18.2% vs Prior Month | F7: ▼ Controlled at 34.4% | H7: ▲ 59.0% Margin | J7: ▲ 47.2% Net Margin
B8: 💲 Revenue
D9: EXECUTIVE PROFIT & LOSS (P&L) STATEMENT (May 2024)
D10: Line Item | E10: May Actual ($) | F10: May Budget ($) | G10: Variance ($) | H10: % of Revenue | I10: YTD Total ($)
B11: 📈 Profitability | D11: Gross Revenue | E11: =Raw_Data!E16 -> 0 | F11: 8500000 | G11: =E11-F11 -> 0 | H11: 100.0% | I11: 43102000
D12: Cost of Goods Sold (COGS) | E12: =Raw_Data!F16 -> 0 | F12: 650000 | G12: =E12-F12 -> 0 | H12: =E12/E11 -> 0 | I12: 3037000
D13: Gross Profit | E13: =E11-E12 -> 0 | F13: 7850000 | G13: =E13-F13 -> 0 | H13: =E13/E11 -> 0 | I13: 40065000
B14: 🌐 Regional Sales | D14: Research & Development (R&D) | E14: 1250000 | F14: 1300000 | G14: =E14-F14 -> 0 | H14: =E14/E11 -> 0 | I14: 6100000
D15: Sales & Marketing (S&M) | E15: 1420000 | F15: 1400000 | G15: =E15-F15 -> 0 | H15: =E15/E11 -> 0 | I15: 6950000
D16: General & Administrative (G&A) | E16: 510000 | F16: 520000 | G16: =E16-F16 -> 0 | H16: =E16/E11 -> 0 | I16: 2500000
B17: 📦 Products | D17: Total Operating Expenses (OpEx) | E17: =SUM(E14:E16) -> 0 | F17: 3220000 | G17: =E17-F17 -> 0 | H17: =E17/E11 -> 0 | I17: 15550000
D18: Operating Income (EBITDA) | E18: =E13-E17 -> 0 | F18: 4630000 | G18: =E18-F18 -> 0 | H18: =E18/E11 -> 0 | I18: 24515000
D19: Income Tax Expense (20%) | E19: =E18*0.20 -> 0 | F19: 926000 | G19: =E19-F19 -> 0 | H19: =E19/E11 -> 0 | I19: 4903000
B20: 📥 Export to PDF | D20: Net Income | E20: =E18-E19 -> 0 | F20: 3704000 | G20: =E20-F20 -> 0 | H20: =E20/E11 -> 0 | I20: 19612000

Sheet Regional_Sales
B2: ▍▍▍ PERFORMX | D2: GLOBAL TERRITORIES & REGIONAL INTELLIGENCE
B3: INSIGHT. ANALYZE. GROW | D3: Geographic Distribution, Quota Attainment & Global Market Penetration
B5: 📊 Dashboard | D5: NORTH AMERICA | F5: EMEA REGION | H5: ASIA PACIFIC (APAC) | J5: LATAM & MEA
D6: $4,808,960 | F6: $2,450,720 | H6: $1,387,200 | J6: $601,120
D7: 52.0% Global Share | F7: 26.5% Global Share | H7: 15.0% Global Share | J7: 6.5% Global Share
B8: 💲 Revenue
D9: REGIONAL QUOTA ATTAINMENT & EXPANSION PIPELINE
D10: Territory | E10: Regional Lead | F10: Monthly Quota ($) | G10: May Revenue ($) | H10: Attainment % | I10: Active Accounts | J10: YoY Growth %
B11: 📈 Profitability | D11: North America (US & Canada) | E11: David Vance | F11: 4500000 | G11: 4808960 | H11: =G11/F11 -> 0 | I11: 1420 | J11: 0.185
D12: Western Europe (EMEA) | E12: Elena Rostova | F12: 2300000 | G12: 2450720 | H12: =G12/F12 -> 0 | I12: 890 | J12: 0.224
D13: Asia Pacific (APAC) | E13: Kenji Sato | F13: 1300000 | G13: 1387200 | H13: =G13/F13 -> 0 | I13: 540 | J13: 0.312
B14: 🌐 Regional Sales | D14: Latin America (LATAM) | E14: Carlos Silva | F14: 350000 | G14: 375400 | H14: =G14/F14 -> 0 | I14: 210 | J14: 0.148
D15: Middle East & Africa (MEA) | E15: Tariq Mansoor | F15: 200000 | G15: 225720 | H15: =G15/F15 -> 0 | I15: 135 | J15: 0.286
B17: 📦 Products
B20: 📥 Export to PDF

Sheet Products
B2: ▍▍▍ PERFORMX | D2: PRODUCT LINE PERFORMANCE & TIER MATRIX
B3: INSIGHT. ANALYZE. GROW | D3: SKU Performance, Unit Economics & Customer Lifetime Value (LTV)
B5: 📊 Dashboard | D5: ENTERPRISE SUITE | F5: CLOUD API CALLS | H5: OVERALL GROSS MARGIN | J5: LOGO CHURN RATE
D6: $5,733,760 | F6: 48,250,000 | H6: 78.5% | J6: 0.65%
D7: 62.0% Revenue Share | F7: ▲ 32.1% YoY Volume | H7: ▲ Software Tier Model | J7: ▼ Best-in-Class SaaS
B8: 💲 Revenue
D9: PRODUCT PORTFOLIO & REVENUE GENERATION MATRIX
D10: Product Line SKU | E10: Target Segment | F10: Subscribed Units | G10: Price / Unit ($) | H10: May Revenue ($) | I10: Revenue Share % | J10: Gross Margin %
B11: 📈 Profitability | D11: Enterprise Analytics Core | E11: Enterprise | F11: 112 | G11: 51200 | H11: 5733760 | I11: 0.62 | J11: 0.825
D12: Commercial Team Suite | E12: Mid-Market | F12: 445 | G12: 4780 | H12: 2127040 | I12: 0.23 | J12: 0.742
D13: SMB Cloud Pro | E13: Small Business | F13: 1850 | G13: 500 | H13: 924800 | I13: 0.1 | J13: 0.685
B14: 🌐 Regional Sales | D14: Professional Implementation | E14: All Tiers | F14: 24 | G14: 15000 | H14: 360000 | I14: 0.039 | J14: 0.45
D15: Cybersecurity & SLA Add-on | E15: Enterprise | F15: 85 | G15: 1200 | H15: 102400 | I15: 0.011 | J15: 0.91
B17: 📦 Products
B20: 📥 Export to PDF

Sheet Raw_Data
B2: ▍▍▍ PERFORMX | D2: TRANSACTIONAL & MASTER INPUT DATA ENGINE
B3: INSIGHT. ANALYZE. GROW | D3: Live Operational Input: Modify any cell below to watch all KPIs, Charts & Tables update automatically.
B5: 📊 Dashboard | D5: 1. MASTER TIMELINE PERFORMANCE TABLE (Apr – May 2024)
D6: Date | E6: Revenue ($) | F6: Cost ($) | G6: Gross Profit ($) | H6: Gross Margin % | I6: Prior Revenue ($) | J6: Prior Cost ($) | K6: Prior Profit ($) | L6: Budget Rev ($) | M6: Budget Cost ($) | N6: Budget Profit ($) | O6: YTD Rev ($)
D7: Apr 1 | E7: 4000000 | F7: 450000 | G7: 3550000 | H7: =G7/E7 -> 0 | I7: 3600000 | J7: 430000 | K7: 3170000 | L7: 3800000 | M7: 440000 | N7: 3360000 | O7: 22000000
B8: 💲 Revenue | D8: Apr 8 | E8: 4800000 | F8: 480000 | G8: 4320000 | H8: =G8/E8 -> 0 | I8: 4200000 | J8: 460000 | K8: 3740000 | L8: 4500000 | M8: 470000 | N8: 4030000 | O8: 26800000
D9: Apr 15 | E9: 5600000 | F9: 520000 | G9: 5080000 | H9: =G9/E9 -> 0 | I9: 5000000 | J9: 500000 | K9: 4500000 | L9: 5200000 | M9: 510000 | N9: 4690000 | O9: 32400000
D10: Apr 22 | E10: 6200000 | F10: 550000 | G10: 5650000 | H10: =G10/E10 -> 0 | I10: 5800000 | J10: 530000 | K10: 5270000 | L10: 6000000 | M10: 540000 | N10: 5460000 | O10: 38600000
B11: 📈 Profitability | D11: Apr 29 | E11: 7200000 | F11: 580000 | G11: 6620000 | H11: =G11/E11 -> 0 | I11: 6500000 | J11: 560000 | K11: 5940000 | L11: 6800000 | M11: 570000 | N11: 6230000 | O11: 45800000
D12: May 6 | E12: 7500000 | F12: 590000 | G12: 6910000 | H12: =G12/E12 -> 0 | I12: 7000000 | J12: 5800000 | K12: 6420000 | L12: 7200000 | M12: 585000 | N12: 6615000 | O12: 53300000
D13: May 13 | E13: 7400000 | F13: 600000 | G13: 6800000 | H13: =G13/E13 -> 0 | I13: 7200000 | J13: 590000 | K13: 6610000 | L13: 7500000 | M13: 600000 | N13: 6900000 | O13: 60700000
B14: 🌐 Regional Sales | D14: May 20 | E14: 8100000 | F14: 610000 | G14: 7490000 | H14: =G14/E14 -> 0 | I14: 7600000 | J14: 600000 | K14: 7000000 | L14: 7800000 | M14: 610000 | N14: 7190000 | O14: 68800000
D15: May 27 | E15: 8700000 | F15: 620000 | G15: 8080000 | H15: =G15/E15 -> 0 | I15: 8000000 | J15: 610000 | K15: 7390000 | L15: 8200000 | M15: 620000 | N15: 7580000 | O15: 77500000
D16: May 31 | E16: 9248000 | F16: 612000 | G16: 9560 | H16: =G16/E16 -> 0 | I16: 8223000 | J16: 648000 | K16: 7575 | L16: 8500000 | M16: 650000 | N16: 7850 | O16: 43102000
B17: 📦 Products
D18: 2. REVENUE BY SEGMENT MASTER TABLE | H18: 3. CHANNEL ACQUISITION PERFORMANCE
D19: Segment | E19: Share % | F19: Allocated Revenue ($) | H19: Channel | I19: Revenue ($) | J19: Formatted (K)
B20: 📥 Export to PDF | D20: Enterprise | E20: 0.62 | F20: =E16*E20 -> 0 | H20: Email | I20: 750000 | J20: =I20/1000 -> 0
D21: Commercial | E21: 0.23 | F21: =E16*E21 -> 0 | H21: Social | I21: 700000 | J21: =I21/1000 -> 0
D22: SMB | E22: 0.1 | F22: =E16*E22 -> 0 | H22: Web | I22: 1200000 | J22: =I22/1000 -> 0
D23: Other | E23: 0.05 | F23: =E16*E23 -> 0 | H23: Partners | I23: 1650000 | J23: =I23/1000 -> 0
H24: Direct | I24: 1450000 | J24: =I24/1000 -> 0
H25: Referral | I25: 1950000 | J25: =I25/1000 -> 0
H26: Other | I26: 2100000 | J26: =I26/1000 -> 0

Sheet Export_Report
B2: ▍▍▍ PERFORMX | D2: EXECUTIVE PERFORMANCE REPORT - PDF EXPORT VIEW
B3: INSIGHT. ANALYZE. GROW | D3: Official C-Suite Financial Summary • Pre-configured for 1-Click Print & PDF Generation
B5: 📊 Dashboard | D5: 🚀 [اضغط هنا لفتح تقرير الـ PDF تلقائياً | CLICK HERE TO OPEN PDF REPORT AUTOMATICALLY]
D7: EXECUTIVE AUDIT SUMMARY
B8: 💲 Revenue
D9: 1. Revenue Performance | E9: Monthly revenue closed at $9.248M, exceeding budget target by +8.8% ($748K favorable variance) with 12.4% MoM expansion.
D10: 2. Cost Containment | E10: Total operating cost held at $612K, representing a -5.7% favorable reduction below the $650K budget allocation.
B11: 📈 Profitability | D11: 3. Profitability Metrics | E11: Gross Profit recorded $9.56K on software services, delivering positive operating cash flow.
D12: 4. Territory & Product Leaders | E12: North America represented 52.0% of total bookings. Enterprise Core Suite remains the primary growth catalyst at 62.0% share.
D13: EXECUTIVE FINANCIAL SCORECARD (CONSOLIDATED)
B14: 🌐 Regional Sales
D15: Key Metric | E15: Actual ($) | F15: Budget ($) | G15: Variance ($) | H15: Attainment % | I15: Prior Period ($) | J15: Growth %
D16: Total Gross Revenue | E16: 9248000 | F16: 8500000 | G16: 748000 | H16: 1.088 | I16: 8223000 | J16: 0.124
B17: 📦 Products | D17: Total Cost of Delivery | E17: 612000 | F17: 650000 | G17: -38000 | H17: 0.941 | I17: 648000 | J17: -0.057
D18: Gross Operating Margin | E18: 8636000 | F18: 7850000 | G18: 786000 | H18: 1.1 | I18: 7575000 | J18: 0.14
D19: EBITDA | E19: 5456000 | F19: 4630000 | G19: 826000 | H19: 1.178 | I19: 4520000 | J19: 0.207
B20: 📥 Export to PDF | D20: Net Income (Post-Tax) | E20: 4364800 | F20: 3704000 | G20: 660800 | H20: 1.178 | I20: 3616000 | J20: 0.207
D22: Report certified by Corporate FP&A • Data verified against transaction ledger. | K22: Signed & Released: May 31, 2024
